{"otherData": {},"traceEvents":[{"cat":"function","dur":42,"name":"void __cdecl Kure::WindowsWindow::SetVSync(bool)","ph":"X","pid":0,"tid":12103975928759698878,"ts":664705321255},{"cat":"function","dur":214836,"name":"void __cdecl Kure::WindowsWindow::Init(const struct Kure::WindowProps &)","ph":"X","pid":0,"tid":12103975928759698878,"ts":664705106661},{"cat":"function","dur":18,"name":"void __cdecl Kure::WindowsWindow::SetVSync(bool)","ph":"X","pid":0,"tid":12103975928759698878,"ts":664705321546},{"cat":"function","dur":9,"name":"void __cdecl Kure::OpenGLVertexBuffer::Bind(void) const","ph":"X","pid":0,"tid":12103975928759698878,"ts":664705321782},{"cat":"function","dur":486,"name":"__cdecl Kure::OpenGLVertexBuffer::OpenGLVertexBuffer(unsigned int)","ph":"X","pid":0,"tid":12103975928759698878,"ts":664705321704},{"cat":"function","dur":1,"name":"void __cdecl Kure::OpenGLVertexBuffer::Bind(void) const","ph":"X","pid":0,"tid":12103975928759698878,"ts":664705322278},{"cat":"function","dur":1,"name":"void __cdecl Kure::OpenGLIndexBuffer::Bind(void) const","ph":"X","pid":0,"tid":12103975928759698878,"ts":664705323439},{"cat":"function","dur":805,"name":"__cdecl Kure::OpenGLIndexBuffer::OpenGLIndexBuffer(unsigned int *,unsigned int)","ph":"X","pid":0,"tid":12103975928759698878,"ts":664705323424},{"cat":"function","dur":716,"name":"class std::basic_string<char,struct std::char_traits<char>,class std::allocator<char> > __cdecl Kure::OpenGLShader::ReadFile(const class std::basic_string<char,struct std::char_traits<char>,class std::allocator<char> > &)","ph":"X","pid":0,"tid":12103975928759698878,"ts":664705324496},{"cat":"function","dur":36,"name":"class std::unordered_map<unsigned int,class std::basic_string<char,struct std::char_traits<char>,class std::allocator<char> >,struct std::hash<unsigned int>,struct std::equal_to<unsigned int>,class std::allocator<struct std::pair<unsigned int const ,class std::basic_string<char,struct std::char_traits<char>,class std::allocator<char> > > > > __cdecl Kure::OpenGLShader::PreProcess(const class std::basic_string<char,struct std::char_traits<char>,class std::allocator<char> > &)","ph":"X","pid":0,"tid":12103975928759698878,"ts":664705325291},{"cat":"function","dur":37788,"name":"void __cdecl Kure::OpenGLShader::Compile(const class std::unordered_map<unsigned int,class std::basic_string<char,struct std::char_traits<char>,class std::allocator<char> >,struct std::hash<unsigned int>,struct std::equal_to<unsigned int>,class std::allocator<struct std::pair<unsigned int const ,class std::basic_string<char,struct std::char_traits<char>,class std::allocator<char> > > > > &)","ph":"X","pid":0,"tid":12103975928759698878,"ts":664705325395},{"cat":"function","dur":38880,"name":"__cdecl Kure::OpenGLShader::OpenGLShader(const class std::basic_string<char,struct std::char_traits<char>,class std::allocator<char> > &)","ph":"X","pid":0,"tid":12103975928759698878,"ts":664705324478},{"cat":"function","dur":48,"name":"void __cdecl Kure::OpenGLShader::Bind(void) const","ph":"X","pid":0,"tid":12103975928759698878,"ts":664705363394},{"cat":"function","dur":44,"name":"void __cdecl Kure::OpenGLShader::SetIntArray(int *,unsigned int,const class std::basic_string<char,struct std::char_traits<char>,class std::allocator<char> > &)","ph":"X","pid":0,"tid":12103975928759698878,"ts":664705363478},{"cat":"function","dur":510,"name":"__cdecl Kure::OpenGLTexture2D::OpenGLTexture2D(unsigned int,unsigned int)","ph":"X","pid":0,"tid":12103975928759698878,"ts":664705363560},{"cat":"function","dur":289,"name":"void __cdecl Kure::OpenGLTexture2D::SetData(void *,unsigned int)","ph":"X","pid":0,"tid":12103975928759698878,"ts":664705364209},{"cat":"function","dur":42889,"name":"void __cdecl Kure::Renderer2D::Init(void)","ph":"X","pid":0,"tid":12103975928759698878,"ts":664705321668},{"cat":"function","dur":798,"name":"void __cdecl Kure::Application::PushOverlay(class Kure::Layer *)","ph":"X","pid":0,"tid":12103975928759698878,"ts":664705364610},{"cat":"function","dur":258846,"name":"__cdecl Kure::Application::Application(const class std::basic_string<char,struct std::char_traits<char>,class std::allocator<char> > &)","ph":"X","pid":0,"tid":12103975928759698878,"ts":664705106651},{"cat":"function","dur":0,"name":"__cdecl Kure::EditorLayer::EditorLayer(void)","ph":"X","pid":0,"tid":12103975928759698878,"ts":664705365715},{"cat":"function","dur":12957,"name":"__cdecl Kure::OpenGLTexture2D::OpenGLTexture2D(const class std::basic_string<char,struct std::char_traits<char>,class std::allocator<char> > &)","ph":"X","pid":0,"tid":12103975928759698878,"ts":664705365802},{"cat":"function","dur":180448,"name":"__cdecl Kure::OpenGLTexture2D::OpenGLTexture2D(const class std::basic_string<char,struct std::char_traits<char>,class std::allocator<char> > &)","ph":"X","pid":0,"tid":12103975928759698878,"ts":664705378866},{"cat":"function","dur":5453,"name":"__cdecl Kure::OpenGLTexture2D::OpenGLTexture2D(const class std::basic_string<char,struct std::char_traits<char>,class std::allocator<char> > &)","ph":"X","pid":0,"tid":12103975928759698878,"ts":664705559445},{"cat":"function","dur":201353,"name":"void __cdecl Kure::EditorLayer::OnAttach(void)","ph":"X","pid":0,"tid":12103975928759698878,"ts":664705365800},{"cat":"function","dur":201442,"name":"void __cdecl Kure::Application::PushLayer(class Kure::Layer *)","ph":"X","pid":0,"tid":12103975928759698878,"ts":664705365776}]}